bidpom/__init__.py
bidpom/bidpom.py
bidpom/pages/__init__.py
bidpom/pages/base.py
bidpom/pages/complete_registration.py
bidpom/pages/reset_password.py
bidpom/pages/sign_in.py
bidpom-2.0.1.dist-info/DESCRIPTION.rst
bidpom-2.0.1.dist-info/METADATA
bidpom-2.0.1.dist-info/RECORD
bidpom-2.0.1.dist-info/WHEEL
bidpom-2.0.1.dist-info/metadata.json
bidpom-2.0.1.dist-info/top_level.txt
browserid/__init__.py
browserid/browser_id.py
browserid/pages/__init__.py
browserid/pages/base.py
browserid/pages/complete_registration.py
browserid/pages/reset_password.py
browserid/pages/sign_in.py
