Metadata-Version: 2.0
Name: bidpom
Version: 2.0.1
Summary: Mozilla BrowserID (Persona) Page Object Model
Home-page: https://github.com/mozilla/bidpom
Author: Mozilla Web QA
Author-email: mozwebqa@mozilla.org
License: Mozilla Public License 2.0 (MPL 2.0)
Keywords: mozilla browserid bidpom persona page object model selenium
Platform: UNKNOWN
Classifier: Development Status :: 5 - Production/Stable
Classifier: Intended Audience :: Developers
Classifier: License :: OSI Approved :: Mozilla Public License 2.0 (MPL 2.0)
Classifier: Operating System :: POSIX
Classifier: Operating System :: Microsoft :: Windows
Classifier: Operating System :: MacOS :: MacOS X
Classifier: Topic :: Software Development :: Quality Assurance
Classifier: Topic :: Software Development :: Testing
Classifier: Topic :: Utilities
Classifier: Programming Language :: Python
Classifier: Programming Language :: Python :: 2.6
Classifier: Programming Language :: Python :: 2.7
Classifier: Programming Language :: Python :: 3.2
Classifier: Programming Language :: Python :: 3.3
Classifier: Programming Language :: Python :: 3.4
Requires-Dist: PyPOM
